{"363419":"tags","15394694":"“A belief is like a guillotine, just as heavy, just as light.”","148b4a45":"Close Modal","462ff49":"Login","7b0776c8":"Your Story","-37e2eff6":"Profiles","7a59368f":"Donate","3c8934e":"Apply","3d503d2b":"No items found.","-b171810":"subhead here","69f71889":"University of","6bf022be":"South Carolina","42628b2":"Hello","39e45e41":"\"Learn as if you were to live forever.\"","6af22973":"Heading 1","6af22974":"Heading 2","6af22975":"Heading 3","6af22976":"Heading 4","6af22977":"Heading 5","6af22978":"Heading 6","36f186d6":"Lorem ipsum dolor sit amet, consectetur adipiscing elit, sed do eiusmod tempor incididunt ut labore et dolore magna aliqua. Ut enim ad minim veniam, quis nostrud exercitation ullamco laboris nisi ut aliquip ex ea commodo consequat. Duis aute irure dolor in reprehenderit in voluptate velit esse cillum dolore eu fugiat nulla pariatur.","40f76109":"Block quote","670f3891":"Ordered list","-7cdc0d7c":"Item 1","-7cdc0d7b":"Item 2","-7cdc0d7a":"Item 3","-27cb5e56":"Unordered list","-7cdc0d6c":"Item A","-7cdc0d6b":"Item B","-7cdc0d6a":"Item C","361eaeed":"Text link","4205e5c8":"Bold text","4abe799c":"Emphasis","1dea1fe6":"Superscript","-69de0115":"Subscript","-6b52b3c5":"Mahatma","4aa61b43":"Colgate Welcome Gift","-3f7b7137":"Claim the Offer","7de776bf":"Franz ","58c0101c":"“Half the Sky”","12d3b":"Mao","-64d3b955":"“No one can construct for you the bridge upon which precisely you must cross the stream of life, no one but you yourself alone.”","5c3b0316":"Frederich","2672cfe4":"“All animals are equal, but some animals are more equal than others.”","7eeb87ff":"George","-1cb07d10":"“I dwell in possibility…”","3ff79ee":"Emily","-42cf24b5":"“Atticus told me to delete the adjectives and I'd have the facts.”","-3ba9430":"Harper Lee","-1a2819cc":"Navigation","-25a4a444":"The footer marks the end of the scroll, but not the end of the story.","f16b659":"( Concept )","-5573b900":"Parallax adds a sense of depth and motion that feels natural to the human eye. By shifting elements at different speeds, we create a layered world that reacts to scroll. It’s subtle, but powerful — turning static sections into dynamic experiences.","357b8a28":"Scroll down ↓","5a2a9eb5":"( Pages )","2268ff":"Home","13ede05":"Resources","3c2336d":"About","7397cc93":"Platform","177bfb17":"( Socials )","4b0ff13e":"LinkedIn","792b2792":"Instagram","3677a79c":"X/Twitter","2bdad211":"( Contact )","-5f73d952":"hello@email","-45ac629d":"Not your typical platform","-2923d15d":"register","119ca21b":"FIRST NAME","1c6105d5":"LAST NAME","4889ba9b":"password","3f0537c":"EMAIL","-5a4b1ccc":"Already Registered?  Login","5a0ea5a1":"Thank you! Your submission has been received!","-7c112e99":"Oops! Something went wrong while submitting the form.","-27cddc30":"submit your story","337a8b":"name","5c24b9c":"email","-65028885":"story summary","-27b638a5":"permission to publish","70b87474":"I agree to Privacy Link and Terms of Use","-5f00d562":"edit your story","7a20d721":"let's go","7f274abe":"Contact us","-ee548a7":"upload documents","35dafd":"show","6dad9f4d":"I agree to terms","2bfd368c":"Reset Password","-e10db":"Welcome Back","-751e9c4d":"Please Login","5d62a953":"@2026 University of South Carolina"}